vto_core/__init__.py
vto_core/apps.py
vto_core/urls.py
vto_core/admin/__init__.py
vto_core/admin/dem_a.py
vto_core/admin/tzn_a.py
vto_core/admin/usr_a.py
vto_core/migrations/0001_initial.py
vto_core/migrations/__init__.py
vto_core/models/__init__.py
vto_core/models/dem_m.py
vto_core/models/tzn_m.py
vto_core/models/usr_m.py
vto_core/templates/admin/base.html
vto_core/templates/admin/base_site.html
vto_core/templates/registration/login.html
vto_core/templates/time/demo-ts-list.dtl
vto_core/templates/time/tz_list.dtl
vto_core/templatetags/markdown_extras.py
vto_core/views/__init__.py
vto_core/views/dem_v.py
vto_core/views/tzn_v.py
vto_core-0.0.3.2.dist-info/METADATA
vto_core-0.0.3.2.dist-info/WHEEL
vto_core-0.0.3.2.dist-info/licenses/LICENSE
vto_core-0.0.3.2.dist-info/RECORD
