Metadata-Version: 2.4
Name: vto-core
Version: 0.0.3.2
Summary: This is a custom reusable Django core app.
Project-URL: Repository, https://github.com/venteto/vto-core
License-Expression: MIT
License-File: LICENSE
Requires-Python: >=3.13
Requires-Dist: markdown-link-attr-modifier>=0.2.1
Requires-Dist: markdown>=3.7
